dutchtext2num-0.1.1.dist-info/METADATA
dutchtext2num-0.1.1.dist-info/WHEEL
dutchtext2num/__init__.py
dutchtext2num/dutchtext2num.cpython-311-x86_64-linux-gnu.so
dutchtext2num-0.1.1.dist-info/RECORD
